[
  {
    "_id": { "$oid": "637ebcac50832e0655c08d20" },
    "state_name": "آذربایجان شرقی"
  },
  {
    "_id": { "$oid": "637ebcac50832e0655c08d23" },
    "state_name": "اصفهان"
  },
  {
    "_id": { "$oid": "637ebcac50832e0655c08d24" },
    "state_name": "البرز"
  },
  {
    "_id": { "$oid": "637ebcac50832e0655c08d2c" },
    "state_name": "خوزستان"
  },
  {
    "_id": { "$oid": "637ebcac50832e0655c08d2d" },
    "state_name": "زنجان"
  },
  {
    "_id": { "$oid": "637ebcac50832e0655c08d2e" },
    "state_name": "سمنان"
  },
  {
    "_id": { "$oid": "637ebcac50832e0655c08d37" },
    "state_name": "گلستان"
  },
  {
    "_id": { "$oid": "637ebcac50832e0655c08d38" },
    "state_name": "گیلان"
  },
  {
    "_id": { "$oid": "637ebcac50832e0655c08d21" },
    "state_name": "آذربایجان غربی"
  },
  {
    "_id": { "$oid": "637ebcac50832e0655c08d22" },
    "state_name": "اردبیل"
  },
  {
    "_id": { "$oid": "637ebcac50832e0655c08d25" },
    "state_name": "ایلام"
  },
  {
    "_id": { "$oid": "637ebcac50832e0655c08d2b" },
    "state_name": "خراسان شمالی"
  },
  {
    "_id": { "$oid": "637ebcac50832e0655c08d30" },
    "state_name": "فارس"
  },
  {
    "_id": { "$oid": "637ebcac50832e0655c08d34" },
    "state_name": "کرمان"
  },
  {
    "_id": { "$oid": "637ebcac50832e0655c08d3b" },
    "state_name": "مرکزی"
  },
  {
    "_id": { "$oid": "637ebcac50832e0655c08d26" },
    "state_name": "بوشهر"
  },
  {
    "_id": { "$oid": "637ebcac50832e0655c08d27" },
    "state_name": "تهران"
  },
  {
    "_id": { "$oid": "637ebcac50832e0655c08d28" },
    "state_name": "چهارمحال و بختیاری"
  },
  {
    "_id": { "$oid": "637ebcac50832e0655c08d29" },
    "state_name": "خراسان جنوبی"
  },
  {
    "_id": { "$oid": "637ebcac50832e0655c08d2a" },
    "state_name": "خراسان رضوی"
  },
  {
    "_id": { "$oid": "637ebcac50832e0655c08d32" },
    "state_name": "قم"
  },
  {
    "_id": { "$oid": "637ebcac50832e0655c08d35" },
    "state_name": "کرمانشاه"
  },
  {
    "_id": { "$oid": "637ebcac50832e0655c08d3c" },
    "state_name": "هرمزگان"
  },
  {
    "_id": { "$oid": "637ebcac50832e0655c08d3d" },
    "state_name": "همدان"
  },
  {
    "_id": { "$oid": "637ebcac50832e0655c08d2f" },
    "state_name": "سیستان و بلوچستان"
  },
  {
    "_id": { "$oid": "637ebcac50832e0655c08d31" },
    "state_name": "قزوین"
  },
  {
    "_id": { "$oid": "637ebcac50832e0655c08d33" },
    "state_name": "کردستان"
  },
  {
    "_id": { "$oid": "637ebcac50832e0655c08d36" },
    "state_name": "کهگیلویه وبویراحمد"
  },
  {
    "_id": { "$oid": "637ebcac50832e0655c08d39" },
    "state_name": "لرستان"
  },
  {
    "_id": { "$oid": "637ebcac50832e0655c08d3a" },
    "state_name": "مازندران"
  },
  {
    "_id": { "$oid": "637ebcac50832e0655c08d3e" },
    "state_name": "یزد"
  }
]
